{"cameraMode":{"drawMode":0,"name":"Shaded","section":"Shading Mode"},"sceneLighting":true,"audioPlay":false,"sceneViewState":{"showFog":true,"showMaterialUpdate":false,"showSkybox":true,"showFlares":true,"showImageEffects":true,"showParticleSystems":true},"in2DMode":false,"pivot":{"x":409.24725341796877,"y":513.0406494140625,"z":280.44281005859377},"rotation":{"x":0.074296735227108,"y":0.029912110418081285,"z":-0.0022295983508229257,"w":0.9967866539955139},"size":1102.4263916015625,"orthographic":false}